docx_report_formatter/__init__.py
word_report_formatter-0.0.5.dist-info/METADATA
word_report_formatter-0.0.5.dist-info/WHEEL
word_report_formatter-0.0.5.dist-info/top_level.txt
word_report_formatter-0.0.5.dist-info/RECORD
